laserdato/__init__.py
laserdato/align.py
laserdato/get_model.py
laserdato/laser.py
laserdato/embed/embed.py
laserdato/embed/encoder.py
laserdato/embed/laserLstmEncoder.py
laserdato/embed/laserTransformerEncoder.py
laserdato/embed/multiGpuEncoder.py
laserdato/lib/__init__.py
laserdato/lib/constants.py
laserdato/lib/text_processing.py
laserdato-0.1.2.dist-info/METADATA
laserdato-0.1.2.dist-info/WHEEL
laserdato-0.1.2.dist-info/licenses/LICENSE
laserdato-0.1.2.dist-info/RECORD
