Metadata-Version: 2.1
Name: laserdato
Version: 0.1.2
Summary: A small example package
Author: temp
License-File: LICENSE
Classifier: License :: OSI Approved :: MIT License
Classifier: Operating System :: OS Independent
Classifier: Programming Language :: Python :: 3.7
Requires-Python: >=3.7
Requires-Dist: fairseq
Requires-Dist: faiss-cpu
Requires-Dist: ftfy
Requires-Dist: mosestokenizer
Requires-Dist: numpy
Requires-Dist: requests
Requires-Dist: sentencepiece
Requires-Dist: torch~=2.0.1
